{
  "_comment": "키워드별 정적 메타데이터. color/category/description은 수동 큐레이션 값이며, 실제 검색 추이(data, changeRate)는 scripts/fetch_naver_trends.py가 네이버 데이터랩 API로 채워 data/keyword_trends.json을 생성합니다. 키워드를 추가/삭제하려면 이 파일만 수정하면 됩니다 (최대 20개, 네이버 API 호출은 5개씩 배치 처리).",
  "keywords": {
    "흑임자": {
      "color": "#ea580c",
      "category": "전체",
      "description": "건강·고소한 맛 트렌드 핵심 키워드. 빙그레·파리바게뜨 등 대형 브랜드 동시 출시로 가속화."
    },
    "유자": {
      "color": "#b45309",
      "category": "음료",
      "description": "상큼한 감귤계 과일 맛. 여름 시즌 수요와 함께 급부상, 음료·제과 전방위 확산 중."
    },
    "제로슈거": {
      "color": "#0d9488",
      "category": "음료",
      "description": "건강 의식 소비자의 설탕 대체 수요 폭발. 음료 카테고리 전체를 관통하는 메가 트렌드."
    },
    "마라": {
      "color": "#e11d48",
      "category": "라면/스낵",
      "description": "매운 향신료 조합, 지속적 강세. 마라+크림, 마라+로제 등 하이브리드 변형이 새 기회."
    },
    "트러플": {
      "color": "#7c3aed",
      "category": "스낵/빙과",
      "description": "프리미엄 식재료의 대중화. 스낵·빙과 영역에서 고급화 포지셔닝 수단으로 각광."
    },
    "쑥": {
      "color": "#15803d",
      "category": "베이커리/제과",
      "description": "전통 한식 식재료의 현대적 재해석. 2세대 K-FOOD 트렌드의 핵심 키워드."
    },
    "얼그레이": {
      "color": "#2563eb",
      "category": "음료/제과",
      "description": "홍차 향미, 고급스러운 이미지. 밀크티 붐과 함께 제과·스낵 전반으로 확산."
    },
    "로제": {
      "color": "#db2777",
      "category": "간편식",
      "description": "크리미 토마토 소스, 간편식 주류. HMR·라면·스낵 전방위 적용 단계."
    },
    "할라피뇨": {
      "color": "#c2410c",
      "category": "스낵",
      "description": "중강도 매운맛 트렌드. 초강렬 매운맛에서 조금 절제된 수준으로 수요 이동."
    },
    "말차": {
      "color": "#16a34a",
      "category": "음료/제과",
      "description": "안정적 성장세, 일본 프리미엄 맛 지속 인기. 음료·베이커리 전반 확산."
    },
    "단짠": {
      "color": "#a16207",
      "category": "스낵",
      "description": "단맛+짠맛 조합, 스낵 카테고리 영구 정착 키워드. 꾸준한 베이스 수요 유지."
    },
    "흑당": {
      "color": "#92400e",
      "category": "음료",
      "description": "2024년 피크 이후 지속 하락. 소비자 피로도 증가, 신제품 출시 자제 필요."
    }
  }
}
